MayuriScanner/__init__.py
MayuriScanner/main.py
MayuriScanner-0.1.dist-info/LICENSE
MayuriScanner-0.1.dist-info/METADATA
MayuriScanner-0.1.dist-info/WHEEL
MayuriScanner-0.1.dist-info/top_level.txt
MayuriScanner-0.1.dist-info/RECORD
