Metadata-Version: 2.1
Name: MayuriScanner
Version: 0.1
Summary: A API bassed telegram scanner.
Home-page: https://github.com/XZeipher/MayuriScanner
Author: Alpha
Author-email: alphacoders@yahoo.com
License: GNU General Public License v3.0
Keywords: telegram,mayuri,bot,api,gban,scan
Classifier: Framework :: AsyncIO
Classifier: Development Status :: 3 - Alpha
Classifier: Intended Audience :: Developers
Classifier: License :: OSI Approved :: GNU General Public License v2 or later (GPLv2+)
Classifier: Natural Language :: English
Classifier: Operating System :: OS Independent
Classifier: Programming Language :: Python :: 3.7
Classifier: Programming Language :: Python :: 3.8
Classifier: Programming Language :: Python :: 3.9
Classifier: Programming Language :: Python :: 3.10
Classifier: Topic :: Internet :: WWW/HTTP
Classifier: Topic :: Software Development :: Libraries
Classifier: Topic :: Software Development :: Build Tools
License-File: LICENSE
Requires-Dist: requests
